yolodetect/__init__.py
yolodetect/detect_image.py
yolodetect/yolo_detector.py
yolodetect/models/__init__.py
yolodetect/models/common.py
yolodetect/models/experimental.py
yolodetect/models/tf.py
yolodetect/models/yolo.py
yolodetect/utils/__init__.py
yolodetect/utils/activations.py
yolodetect/utils/augmentations.py
yolodetect/utils/autoanchor.py
yolodetect/utils/autobatch.py
yolodetect/utils/callbacks.py
yolodetect/utils/datasets.py
yolodetect/utils/downloads.py
yolodetect/utils/general.py
yolodetect/utils/log_conf.py
yolodetect/utils/loss.py
yolodetect/utils/metrics.py
yolodetect/utils/plots.py
yolodetect/utils/torch_utils.py
yolodetect/utils/loggers/__init__.py
detection_yolo-0.0.2.dist-info/LICENSE
detection_yolo-0.0.2.dist-info/METADATA
detection_yolo-0.0.2.dist-info/WHEEL
detection_yolo-0.0.2.dist-info/top_level.txt
detection_yolo-0.0.2.dist-info/RECORD
