Metadata-Version: 2.1
Name: detection-yolo
Version: 0.0.2
License-File: LICENSE
Requires-Dist: ultralytics ==8.0.54
